[
    {
        "id":"01",
        "name":"Уильям «Билли» Бутчер / Мясник"
    },
    {
        "id":"02",
        "name":"Хью «Хьюи» Кэмпбелл"
    },{
        "id":"03",
        "name":"Джон / Хоумлендер"
    },
    {
        "id":"04",
        "name":"Энни Дженьюэри / Старлайт"
    },
    {
        "id":"05",
        "name":"Мэгги Шоу / Королева Мэйв"
    },
    {
        "id":"06",
        "name":"Реджи Франклин / Экспресс"
    },
    {
        "id":"07",
        "name":"Марвин Т. Милк / Молоко Матери / ММ"
    },
    {
        "id":"08",
        "name":"Кевин Московиц / Подводный"
    },
    {
        "id":"09",
        "name":"Серж / Французик"
    },
    {
        "id":"10",
        "name":"Кимико Миясиро / Самка"
    },
    {
        "id":"11",
        "name":"Ирвинг / Чёрный Нуар"
    },
    {
        "id":"12",
        "name":"Мэдлин Стилвелл"
    },
    {
        "id":"13",
        "name":"Эшли Баррет"
    },
    {
        "id":"14",
        "name":"Клара Райзингер / Либерти / Штормфронт"
    },
    {
        "id":"15",
        "name":"Виктория «Вик» Ньюман / Надя"
    },
    {
        "id":"16",
        "name":"Бен / Солдатик"
    }
]